[
    {"name":"8月黄票换抽","sells":"0","originium":"0","orundum":"0","permit":"8","permit10":"3","price":"0.00","type":"store","times":"38"},
    {"name":"9月黄票换抽","sells":"0","originium":"0","orundum":"0","permit":"8","permit10":"3","price":"0.00","type":"store","times":"38"},
    {"name":"10月黄票换抽","sells":"0","originium":"0","orundum":"0","permit":"8","permit10":"3","price":"0.00","type":"store","times":"38"},
    {"name":"11月黄票换抽","sells":"0","originium":"0","orundum":"0","permit":"8","permit10":"3","price":"0.00","type":"store","times":"38"}
]